comun_sqlsrv.py
comun_sqlsrv-0.5.dist-info/METADATA
comun_sqlsrv-0.5.dist-info/WHEEL
comun_sqlsrv-0.5.dist-info/top_level.txt
comun_sqlsrv-0.5.dist-info/RECORD
