Metadata-Version: 2.1
Name: comun_sqlsrv
Version: 0.5
Requires-Dist: pymssql
